// converted by version  [v3.0.5]
// on Sat Nov 11 16:58:54 GMT 2017

.package bo271/test {
	.aid 0xD1:0xD2:0xD3:0xD4:0xD5:0x1;
	.version 1.0;

	.imports {
		0xA0:0x0:0x0:0x0:0x62:0x1:0x1 1.6;		//javacard/framework
		0xA0:0x0:0x0:0x0:0x62:0x0:0x1 1.0;		//java/lang
	}

	.applet {
		0xD1:0xD2:0xD3:0xD4:0xD5 FirstApplet;
	}

	.constantPool {
		// 0
		staticMethodRef FirstApplet/<init>()V;
		// 1
		.classRef FirstApplet;
		// 2
		staticMethodRef 0.3.0()V;		// javacard/framework/Applet.<init>()V
		// 3
		virtualMethodRef 0.3.1()V;		// register()V
		// 4
		virtualMethodRef 0.10.1()[B;		// getBuffer()[B
		// 5
		staticMethodRef 0.7.1(S)V;		// javacard/framework/ISOException.throwIt(S)V
		// 6
		virtualMethodRef 0.10.7()S;		// setOutgoing()S
		// 7
		staticFieldRef short FirstApplet/GET_BALANCE_RESPONSE_SZ;
		// 8
		virtualMethodRef 0.10.8(SS)V;		// setOutgoingAndSend(SS)V
		// 9
		virtualMethodRef 0.10.4(SS)V;		// sendBytes(SS)V
		// 10
		staticMethodRef 1.0.0()V;		// java/lang/Object.<init>()V
	}

	.class public FirstApplet 0 extends 0.3 {		// extends javacard/framework/Applet

		.fields {
			private static short GET_BALANCE_RESPONSE_SZ = 2;		// S
		}

		.publicMethodTable 4 {
			equals(Ljava/lang/Object;)Z;
			register()V;
			register([BSB)V;
			selectingApplet()Z;
			deselect()V;
			getShareableInterfaceObject(Ljavacard/framework/AID;B)Ljavacard/framework/Shareable;;
			select()Z;
			process(Ljavacard/framework/APDU;)V;
		}

		.packageMethodTable 0 {
		}

		.method public static install([BSB)V 0 {
			.stack 1;
			.locals 0;

				L0:	new 1;		// bo271/test/FirstApplet
					invokespecial 0;		// bo271/test/FirstApplet.<init>()V
					return;
		}

		.method protected <init>()V 1 {
			.stack 1;
			.locals 0;

				L0:	aload_0;
					invokespecial 2;		// javacard/framework/Applet.<init>()V
					aload_0;
					invokevirtual 3;		// register()V
					return;
		}

		.method public process(Ljavacard/framework/APDU;)V 7 {
			.stack 3;
			.locals 5;

			.descriptor	Ljavacard/framework/APDU;	0.10;

				L0:	aload_1;
					invokevirtual 4;		// getBuffer()[B
					astore_2;
				L1:	aload_2;
					sconst_0;
					baload;
					sstore_3;
				L2:	aload_2;
					sconst_1;
					baload;
					sstore 4;
				L3:	sload 4;
					bspush 48;
					if_scmpeq L5;
				L4:	sspush 27265;
					invokestatic 5;		// javacard/framework/ISOException.throwIt(S)V
				L5:	sload_3;
					sspush 128;
					if_scmpeq L7;
				L6:	sspush 28160;
					invokestatic 5;		// javacard/framework/ISOException.throwIt(S)V
				L7:	aload_2;
					sconst_4;
					baload;
					sspush 255;
					sand;
					sstore 5;
				L8:	sload 5;
					ifeq L10;
				L9:	sspush 26368;
					invokestatic 5;		// javacard/framework/ISOException.throwIt(S)V
				L10:	aload_1;
					invokevirtual 6;		// setOutgoing()S
					sstore 6;
				L11:	sload 6;
					getstatic_s 7;		// short bo271/test/FirstApplet.GET_BALANCE_RESPONSE_SZ
					if_scmpge L13;
				L12:	sspush 26368;
					invokestatic 5;		// javacard/framework/ISOException.throwIt(S)V
				L13:	aload_2;
					sconst_0;
					sconst_1;
					bastore;
					aload_2;
					sconst_1;
					sconst_2;
					bastore;
					aload_2;
					sconst_3;
					sconst_3;
					bastore;
					aload_1;
					sconst_0;
					sconst_3;
					invokevirtual 8;		// setOutgoingAndSend(SS)V
					aload_1;
					sconst_0;
					sconst_3;
					invokevirtual 9;		// sendBytes(SS)V
					return;
		}

		.method public select()Z 6 {
			.stack 1;
			.locals 0;

				L0:	sconst_1;
					sreturn;
		}

		.method public deselect()V 4 {
			.stack 0;
			.locals 0;

				L0:	return;
		}

	}

	.class final FirstAppletStrings extends 1.0 {		// extends java/lang/Object

		.fields {
			static final byte[] Package = {98,111,50,55,49,46,116,101,115,116};		// [B
			static final byte[] AppletName = {70,105,114,115,116,65,112,112,108,101,116};		// [B
		}

		.publicMethodTable 1 {
			equals(Ljava/lang/Object;)Z;
		}

		.packageMethodTable 0 {
		}

		.method  <init>()V {
			.stack 1;
			.locals 0;

				L0:	aload_0;
					invokespecial 10;		// java/lang/Object.<init>()V
					return;
		}

	}

}
